manus_mobile/__init__.py
manus_mobile/adb_client.py
manus_mobile/core.py
manus_mobile/mobile_computer.py
manus_mobile/tools.py
manus_mobile/ui_dump_parser.py
manus_mobile-0.1.0.dist-info/LICENSE
manus_mobile-0.1.0.dist-info/METADATA
manus_mobile-0.1.0.dist-info/WHEEL
manus_mobile-0.1.0.dist-info/top_level.txt
manus_mobile-0.1.0.dist-info/RECORD
