Metadata-Version: 2.1
Name: manus-mobile
Version: 0.1.0
Summary: Python library for AI-driven mobile device automation
Home-page: https://github.com/femtozheng/manusmobile
Author: FemtoZheng
Author-email: femtozheng@example.com
License: UNKNOWN
Project-URL: Bug Tracker, https://github.com/femtozheng/manusmobile/issues
Project-URL: Documentation, https://github.com/femtozheng/manusmobile#readme
Project-URL: Source Code, https://github.com/femtozheng/manusmobile
Keywords: mobile,android,automation,adb,testing,ai,manus
Platform: UNKNOWN
Classifier: Programming Language :: Python :: 3
Classifier: Programming Language :: Python :: 3.8
Classifier: Programming Language :: Python :: 3.9
Classifier: Programming Language :: Python :: 3.10
Classifier: Programming Language :: Python :: 3.11
Classifier: Operating System :: OS Independent
Classifier: Topic :: Software Development :: Libraries :: Python Modules
Classifier: Topic :: Software Development :: Testing
Classifier: Intended Audience :: Developers
Requires-Python: >=3.8
License-File: LICENSE
Requires-Dist: pydantic>=2.4.2
Requires-Dist: typing-extensions>=4.5.0
Requires-Dist: aiohttp>=3.8.0
Requires-Dist: pillow>=9.0.0
Requires-Dist: numpy>=1.20.0
